{
  "checks": {
    "required_runtime_files": true,
    "required_docs_present": true,
    "learning_bundle_runtime_ready": true,
    "meta_outputs_present": true,
    "translations_present": true,
    "packaging_noise_absent": true,
    "display_i18n_ready": true
  },
  "ready_for_parallel_merge_prep": true,
  "missing_required_runtime_files": [],
  "missing_required_docs": [],
  "missing_meta_outputs": [],
  "packaging": {
    "noise_patterns_checked": [
      "__pycache__",
      "*.pyc",
      "*.pyo",
      ".pytest_cache",
      ".mypy_cache",
      ".ruff_cache",
      ".DS_Store"
    ],
    "noise_items_found_before_cleanup": [
      "__pycache__",
      "__pycache__/app.cpython-313.pyc",
      "scripts/__pycache__",
      "scripts/__pycache__/build_indexes.cpython-313.pyc",
      "scripts/__pycache__/check_display_i18n.cpython-313.pyc",
      "scripts/__pycache__/check_i18n.cpython-313.pyc",
      "scripts/__pycache__/check_integrity.cpython-313.pyc",
      "scripts/__pycache__/check_missing_assets.cpython-313.pyc",
      "scripts/__pycache__/check_packaging_hygiene.cpython-313.pyc",
      "scripts/__pycache__/smoke_check.cpython-313.pyc",
      "scripts/__pycache__/validate_data.cpython-313.pyc",
      "utils/__pycache__",
      "utils/__pycache__/__init__.cpython-313.pyc",
      "utils/__pycache__/assets.cpython-313.pyc",
      "utils/__pycache__/data_access.cpython-313.pyc",
      "utils/__pycache__/i18n.cpython-313.pyc",
      "utils/__pycache__/integrity.cpython-313.pyc",
      "utils/__pycache__/scoring.cpython-313.pyc",
      "utils/__pycache__/terms.cpython-313.pyc"
    ],
    "removed_noise_items": [
      "__pycache__",
      "scripts/__pycache__",
      "utils/__pycache__"
    ],
    "noise_items_found": [],
    "noise_items_remaining_after_cleanup": [],
    "cleanup_performed": true,
    "clean_for_packaging": true,
    "autocontamination_safe": true,
    "notes": [
      "This check removes removable packaging noise before the final scan.",
      "The final cleanliness status reflects the post-cleanup state of the tree."
    ]
  },
  "display_i18n": {
    "locales_checked": [
      "pt-BR",
      "en"
    ],
    "checks": {
      "pt-BR": {
        "guide_display_localized": true,
        "learning_bundle_localized": true,
        "creator_metadata_localized": true
      },
      "en": {
        "guide_display_localized": true,
        "learning_bundle_localized": true,
        "creator_metadata_localized": true
      }
    },
    "failing_checks": {
      "pt-BR": [],
      "en": []
    },
    "display_locale_consistent": true,
    "notes": [
      "This check validates localized display values for guide and learning runtime paths.",
      "It does not render matchup content and does not modify matchup files."
    ]
  },
  "report_consistency": {
    "packaging_report_used_as_single_source_of_truth": true,
    "packaging_report_clean_matches_merge_check": true
  },
  "learning": {
    "learning_bundle_files": {
      "camille_learning.json": {
        "path": "data/learning/camille_learning.json",
        "required": true,
        "status": "ok",
        "missing_required_keys": []
      },
      "camille_combos.json": {
        "path": "data/learning/camille_combos.json",
        "required": false,
        "status": "ok",
        "missing_required_keys": []
      },
      "camille_mechanics.json": {
        "path": "data/learning/camille_mechanics.json",
        "required": false,
        "status": "ok",
        "missing_required_keys": []
      },
      "camille_macro.json": {
        "path": "data/learning/camille_macro.json",
        "required": false,
        "status": "ok",
        "missing_required_keys": []
      },
      "streamers_youtubers.json": {
        "path": "data/meta/streamers_youtubers.json",
        "required": false,
        "status": "ok",
        "missing_required_keys": []
      },
      "camille_build_decision.json": {
        "path": "data/learning/camille_build_decision.json",
        "required": false,
        "status": "ok",
        "missing_required_keys": []
      },
      "camille_runes_decision.json": {
        "path": "data/learning/camille_runes_decision.json",
        "required": false,
        "status": "ok",
        "missing_required_keys": []
      },
      "camille_archetypes.json": {
        "path": "data/learning/camille_archetypes.json",
        "required": false,
        "status": "ok",
        "missing_required_keys": []
      },
      "camille_training_plan.json": {
        "path": "data/learning/camille_training_plan.json",
        "required": false,
        "status": "ok",
        "missing_required_keys": []
      },
      "camille_phase_checklists.json": {
        "path": "data/learning/camille_phase_checklists.json",
        "required": false,
        "status": "ok",
        "missing_required_keys": []
      },
      "camille_faq.json": {
        "path": "data/learning/camille_faq.json",
        "required": false,
        "status": "ok",
        "missing_required_keys": []
      },
      "camille_advanced_interactions.json": {
        "path": "data/learning/camille_advanced_interactions.json",
        "required": false,
        "status": "ok",
        "missing_required_keys": []
      },
      "camille_execution_reference.json": {
        "path": "data/learning/camille_execution_reference.json",
        "required": false,
        "status": "ok",
        "missing_required_keys": []
      },
      "camille_microtips.json": {
        "path": "data/learning/camille_microtips.json",
        "required": false,
        "status": "ok",
        "missing_required_keys": []
      },
      "camille_glossary.json": {
        "path": "data/learning/camille_glossary.json",
        "required": false,
        "status": "ok",
        "missing_required_keys": []
      },
      "camille_practice_scenarios.json": {
        "path": "data/learning/camille_practice_scenarios.json",
        "required": false,
        "status": "ok",
        "missing_required_keys": []
      },
      "camille_coach_paths.json": {
        "path": "data/learning/camille_coach_paths.json",
        "required": false,
        "status": "ok",
        "missing_required_keys": []
      },
      "camille_player_profiles.json": {
        "path": "data/learning/camille_player_profiles.json",
        "required": false,
        "status": "ok",
        "missing_required_keys": []
      },
      "camille_improvement_priorities.json": {
        "path": "data/learning/camille_improvement_priorities.json",
        "required": false,
        "status": "ok",
        "missing_required_keys": []
      },
      "camille_short_training_blocks.json": {
        "path": "data/learning/camille_short_training_blocks.json",
        "required": false,
        "status": "ok",
        "missing_required_keys": []
      },
      "camille_review_checklists.json": {
        "path": "data/learning/camille_review_checklists.json",
        "required": false,
        "status": "ok",
        "missing_required_keys": []
      },
      "camille_common_mistakes.json": {
        "path": "data/learning/camille_common_mistakes.json",
        "required": false,
        "status": "ok",
        "missing_required_keys": []
      },
      "camille_mistake_corrections.json": {
        "path": "data/learning/camille_mistake_corrections.json",
        "required": false,
        "status": "ok",
        "missing_required_keys": []
      },
      "camille_self_review_diagnostics.json": {
        "path": "data/learning/camille_self_review_diagnostics.json",
        "required": false,
        "status": "ok",
        "missing_required_keys": []
      },
      "camille_improvement_matrix.json": {
        "path": "data/learning/camille_improvement_matrix.json",
        "required": false,
        "status": "ok",
        "missing_required_keys": []
      },
      "camille_game_review_triggers.json": {
        "path": "data/learning/camille_game_review_triggers.json",
        "required": false,
        "status": "ok",
        "missing_required_keys": []
      },
      "camille_situational_gameplans.json": {
        "path": "data/learning/camille_situational_gameplans.json",
        "required": false,
        "status": "ok",
        "missing_required_keys": []
      },
      "camille_decision_recovery.json": {
        "path": "data/learning/camille_decision_recovery.json",
        "required": false,
        "status": "ok",
        "missing_required_keys": []
      },
      "camille_adaptation_layers.json": {
        "path": "data/learning/camille_adaptation_layers.json",
        "required": false,
        "status": "ok",
        "missing_required_keys": []
      },
      "camille_state_based_adjustments.json": {
        "path": "data/learning/camille_state_based_adjustments.json",
        "required": false,
        "status": "ok",
        "missing_required_keys": []
      }
    },
    "bundle_runtime_ready": true,
    "bundle_section_coverage": {
      "overview": true,
      "combos": true,
      "mechanics": true,
      "macro": true,
      "creators": true
    },
    "missing_required_files": [],
    "missing_required_keys": {},
    "optional_files_missing_or_invalid": [],
    "optional_files_usable": [
      "camille_adaptation_layers.json",
      "camille_advanced_interactions.json",
      "camille_archetypes.json",
      "camille_build_decision.json",
      "camille_coach_paths.json",
      "camille_combos.json",
      "camille_common_mistakes.json",
      "camille_decision_recovery.json",
      "camille_execution_reference.json",
      "camille_faq.json",
      "camille_game_review_triggers.json",
      "camille_glossary.json",
      "camille_improvement_matrix.json",
      "camille_improvement_priorities.json",
      "camille_macro.json",
      "camille_mechanics.json",
      "camille_microtips.json",
      "camille_mistake_corrections.json",
      "camille_phase_checklists.json",
      "camille_player_profiles.json",
      "camille_practice_scenarios.json",
      "camille_review_checklists.json",
      "camille_runes_decision.json",
      "camille_self_review_diagnostics.json",
      "camille_short_training_blocks.json",
      "camille_situational_gameplans.json",
      "camille_state_based_adjustments.json",
      "camille_training_plan.json",
      "streamers_youtubers.json"
    ],
    "warnings_present": false
  },
  "expected_files_manifest": {
    "required_runtime": [
      {
        "path": "app.py",
        "exists": true
      },
      {
        "path": "requirements.txt",
        "exists": true
      },
      {
        "path": "render.yaml",
        "exists": true
      },
      {
        "path": "templates/base.html",
        "exists": true
      },
      {
        "path": "templates/home.html",
        "exists": true
      },
      {
        "path": "templates/champion_guide.html",
        "exists": true
      },
      {
        "path": "templates/learning.html",
        "exists": true
      },
      {
        "path": "translations/pt-BR.json",
        "exists": true
      },
      {
        "path": "translations/en.json",
        "exists": true
      },
      {
        "path": "utils/data_access.py",
        "exists": true
      },
      {
        "path": "utils/i18n.py",
        "exists": true
      },
      {
        "path": "scripts/validate_data.py",
        "exists": true
      },
      {
        "path": "scripts/build_indexes.py",
        "exists": true
      },
      {
        "path": "scripts/check_missing_assets.py",
        "exists": true
      },
      {
        "path": "scripts/check_integrity.py",
        "exists": true
      },
      {
        "path": "scripts/check_i18n.py",
        "exists": true
      },
      {
        "path": "scripts/check_display_i18n.py",
        "exists": true
      },
      {
        "path": "scripts/smoke_check.py",
        "exists": true
      },
      {
        "path": "scripts/check_packaging_hygiene.py",
        "exists": true
      }
    ],
    "required_docs": [
      {
        "path": "README.md",
        "exists": true
      },
      {
        "path": "pipeline/merge_readiness.md",
        "exists": true
      },
      {
        "path": "pipeline/premerge_predeploy_checklist.md",
        "exists": true
      },
      {
        "path": "pipeline/packaging_hygiene.md",
        "exists": true
      }
    ],
    "optional_learning_inputs": [
      {
        "path": "data/learning/camille_learning.json",
        "exists": true
      },
      {
        "path": "data/learning/camille_combos.json",
        "exists": true
      },
      {
        "path": "data/learning/camille_mechanics.json",
        "exists": true
      },
      {
        "path": "data/learning/camille_macro.json",
        "exists": true
      },
      {
        "path": "data/learning/camille_build_decision.json",
        "exists": true
      },
      {
        "path": "data/learning/camille_runes_decision.json",
        "exists": true
      },
      {
        "path": "data/learning/camille_archetypes.json",
        "exists": true
      },
      {
        "path": "data/learning/camille_training_plan.json",
        "exists": true
      },
      {
        "path": "data/learning/camille_phase_checklists.json",
        "exists": true
      },
      {
        "path": "data/learning/camille_faq.json",
        "exists": true
      },
      {
        "path": "data/learning/camille_advanced_interactions.json",
        "exists": true
      },
      {
        "path": "data/learning/camille_execution_reference.json",
        "exists": true
      },
      {
        "path": "data/learning/camille_microtips.json",
        "exists": true
      },
      {
        "path": "data/learning/camille_glossary.json",
        "exists": true
      },
      {
        "path": "data/learning/camille_practice_scenarios.json",
        "exists": true
      },
      {
        "path": "data/learning/camille_coach_paths.json",
        "exists": true
      },
      {
        "path": "data/learning/camille_player_profiles.json",
        "exists": true
      },
      {
        "path": "data/learning/camille_improvement_priorities.json",
        "exists": true
      },
      {
        "path": "data/learning/camille_short_training_blocks.json",
        "exists": true
      },
      {
        "path": "data/learning/camille_review_checklists.json",
        "exists": true
      },
      {
        "path": "data/learning/camille_common_mistakes.json",
        "exists": true
      },
      {
        "path": "data/learning/camille_mistake_corrections.json",
        "exists": true
      },
      {
        "path": "data/learning/camille_self_review_diagnostics.json",
        "exists": true
      },
      {
        "path": "data/learning/camille_improvement_matrix.json",
        "exists": true
      },
      {
        "path": "data/learning/camille_game_review_triggers.json",
        "exists": true
      },
      {
        "path": "data/learning/camille_situational_gameplans.json",
        "exists": true
      },
      {
        "path": "data/learning/camille_decision_recovery.json",
        "exists": true
      },
      {
        "path": "data/learning/camille_adaptation_layers.json",
        "exists": true
      },
      {
        "path": "data/learning/camille_state_based_adjustments.json",
        "exists": true
      },
      {
        "path": "data/meta/streamers_youtubers.json",
        "exists": true
      }
    ],
    "expected_meta_outputs": [
      {
        "path": "data/meta/assets_report.json",
        "exists": true
      },
      {
        "path": "data/meta/matchups_overview.json",
        "exists": true
      },
      {
        "path": "data/meta/roles_index.json",
        "exists": true
      },
      {
        "path": "data/meta/i18n_report.json",
        "exists": true
      },
      {
        "path": "data/meta/learning_bundle_status.json",
        "exists": true
      },
      {
        "path": "data/meta/learning_integrity_report.json",
        "exists": true
      },
      {
        "path": "data/meta/merge_readiness_report.json",
        "exists": true
      },
      {
        "path": "data/meta/packaging_hygiene_report.json",
        "exists": true
      },
      {
        "path": "data/meta/smoke_check_report.json",
        "exists": true
      },
      {
        "path": "data/meta/premerge_predeploy_checklist.json",
        "exists": true
      },
      {
        "path": "data/meta/display_i18n_report.json",
        "exists": true
      }
    ]
  },
  "readiness_questions": {
    "project_structurally_ready_for_future_merge_inputs": true,
    "learning_ready_for_final_premium_content_absorption": true,
    "principal_line_likely_to_survive_file_level_fusion": true,
    "remaining_gaps_require_manual_review": true
  },
  "manual_review_required": [
    "Comparar arquivo por arquivo os pacotes aprovados antes da fusão final.",
    "Revisar visualmente Home, Entenda a Campeã e /learning após qualquer consolidação.",
    "Confirmar que o conteúdo premium final da paralela 2 encaixa semanticamente nos blocos atuais.",
    "Validar a versão final dos matchups vinda da paralela 1 sem sobrescrever arquivos sistêmicos melhores.",
    "Executar smoke check e revisão manual pré-deploy antes de ativar Render em produção."
  ],
  "notes": [
    "This report prepares the principal line for future approved-package fusion.",
    "It does not perform any merge and does not modify matchup content."
  ]
}
